{
    "timestamp": "2024-01-26 13:06:07",
    "data": [
        {
            "bank": "Kapalicarsi",
            "buy": "30.2900",
            "sell": "30.3000",
            "difference": "0.0100"
        },
        {
            "bank": "Altinkaynak",
            "buy": "30.2910",
            "sell": "30.4330",
            "difference": "0.1420"
        },
        {
            "bank": "Harem",
            "buy": "30.2970",
            "sell": "30.3120",
            "difference": "0.0150"
        },
        {
            "bank": "Odaci",
            "buy": "30.2650",
            "sell": "30.3650",
            "difference": "0.1000"
        },
        {
            "bank": "Venus",
            "buy": "30.2910",
            "sell": "30.3110",
            "difference": "0.0200"
        },
        {
            "bank": "Akbank",
            "buy": "29.5230",
            "sell": "30.8730",
            "difference": "1.3500"
        },
        {
            "bank": "Albaraka Türk",
            "buy": "30.1000",
            "sell": "30.6090",
            "difference": "0.5090"
        },
        {
            "bank": "Alternatif Bank",
            "buy": "30.1700",
            "sell": "30.3170",
            "difference": "0.1470"
        },
        {
            "bank": "Anadolubank",
            "buy": "29.7378",
            "sell": "30.6585",
            "difference": "0.9207"
        },
        {
            "bank": "CEPTETEB",
            "buy": "29.8180",
            "sell": "30.5770",
            "difference": "0.7590"
        },
        {
            "bank": "Denizbank",
            "buy": "29.9802",
            "sell": "30.8303",
            "difference": "0.8501"
        },
        {
            "bank": "Enpara",
            "buy": "29.9500",
            "sell": "30.8000",
            "difference": "0.8500"
        },
        {
            "bank": "Garanti BBVA",
            "buy": "29.7000",
            "sell": "30.8000",
            "difference": "1.1000"
        },
        {
            "bank": "Halkbank",
            "buy": "29.8847",
            "sell": "30.7647",
            "difference": "0.8800"
        },
        {
            "bank": "HSBC",
            "buy": "30.1137",
            "sell": "30.5094",
            "difference": "0.3957"
        },
        {
            "bank": "ING Bank",
            "buy": "29.5931",
            "sell": "30.8136",
            "difference": "1.2205"
        },
        {
            "bank": "İş Bankası",
            "buy": "29.7435",
            "sell": "30.6563",
            "difference": "0.9128"
        },
        {
            "bank": "Kuveyt Turk",
            "buy": "29.9844",
            "sell": "30.3492",
            "difference": "0.3648"
        },
        {
            "bank": "Merkez Bankasi",
            "buy": "30.2343",
            "sell": "30.2888",
            "difference": "0.0545"
        },
        {
            "bank": "QNB Finansbank",
            "buy": "29.9400",
            "sell": "30.8500",
            "difference": "0.9100"
        },
        {
            "bank": "Sekerbank",
            "buy": "29.7360",
            "sell": "30.8540",
            "difference": "1.1180"
        },
        {
            "bank": "Turkiye Finans",
            "buy": "30.0260",
            "sell": "30.5811",
            "difference": "0.5551"
        },
        {
            "bank": "Vakifbank",
            "buy": "29.9120",
            "sell": "30.7630",
            "difference": "0.8510"
        },
        {
            "bank": "Vakif Katilim",
            "buy": "30.0481",
            "sell": "30.5178",
            "difference": "0.4697"
        },
        {
            "bank": "Yapikredi",
            "buy": "29.7933",
            "sell": "30.6885",
            "difference": "0.8952"
        },
        {
            "bank": "Ziraat Bankasi",
            "buy": "29.8942",
            "sell": "30.8057",
            "difference": "0.9115"
        },
        {
            "bank": "Ziraat Katilim",
            "buy": "29.8697",
            "sell": "30.8205",
            "difference": "0.9508"
        }
    ]
}