{
    "timestamp": "2023-05-30 13:44:28",
    "data": [
        {
            "bank": "Kapalicarsi",
            "buy": "20.7000",
            "sell": "20.7500",
            "difference": "0.0500"
        },
        {
            "bank": "Altinkaynak",
            "buy": "20.6550",
            "sell": "20.9690",
            "difference": "0.3140"
        },
        {
            "bank": "Harem",
            "buy": "20.6930",
            "sell": "20.8030",
            "difference": "0.1100"
        },
        {
            "bank": "Odaci",
            "buy": "20.6000",
            "sell": "20.9000",
            "difference": "0.3000"
        },
        {
            "bank": "Venus",
            "buy": "20.6550",
            "sell": "20.8080",
            "difference": "0.1530"
        },
        {
            "bank": "Akbank",
            "buy": "20.3570",
            "sell": "22.4570",
            "difference": "2.1000"
        },
        {
            "bank": "Albaraka Türk",
            "buy": "20.3770",
            "sell": "22.2000",
            "difference": "1.8230"
        },
        {
            "bank": "Denizbank",
            "buy": "20.3800",
            "sell": "22.1801",
            "difference": "1.8001"
        },
        {
            "bank": "Enpara",
            "buy": "20.3225",
            "sell": "21.4975",
            "difference": "1.1750"
        },
        {
            "bank": "Garanti BBVA",
            "buy": "20.3260",
            "sell": "22.2370",
            "difference": "1.9110"
        },
        {
            "bank": "HSBC",
            "buy": "20.3617",
            "sell": "22.1045",
            "difference": "1.7428"
        },
        {
            "bank": "ING Bank",
            "buy": "20.3857",
            "sell": "22.1041",
            "difference": "1.7184"
        }
    ]
}