{
    "timestamp": "2023-07-06 02:02:23",
    "data": [
        {
            "bank": "Kapalicarsi",
            "buy": "26.1200",
            "sell": "26.1400",
            "difference": "0.0200"
        },
        {
            "bank": "Altinkaynak",
            "buy": "26.0280",
            "sell": "26.2760",
            "difference": "0.2480"
        },
        {
            "bank": "Harem",
            "buy": "26.0000",
            "sell": "26.1300",
            "difference": "0.1300"
        },
        {
            "bank": "Odaci",
            "buy": "26.0400",
            "sell": "26.1600",
            "difference": "0.1200"
        },
        {
            "bank": "Venus",
            "buy": "25.9990",
            "sell": "26.2030",
            "difference": "0.2040"
        },
        {
            "bank": "Akbank",
            "buy": "25.1360",
            "sell": "26.9360",
            "difference": "1.8000"
        },
        {
            "bank": "Albaraka Türk",
            "buy": "25.0500",
            "sell": "27.1800",
            "difference": "2.1300"
        },
        {
            "bank": "CEPTETEB",
            "buy": "25.4650",
            "sell": "26.9060",
            "difference": "1.4410"
        },
        {
            "bank": "Denizbank",
            "buy": "25.4032",
            "sell": "26.6033",
            "difference": "1.2001"
        },
        {
            "bank": "Enpara",
            "buy": "25.6450",
            "sell": "26.8460",
            "difference": "1.2010"
        },
        {
            "bank": "Garanti BBVA",
            "buy": "25.2610",
            "sell": "27.0610",
            "difference": "1.8000"
        },
        {
            "bank": "Halkbank",
            "buy": "25.4425",
            "sell": "27.3425",
            "difference": "1.9000"
        },
        {
            "bank": "HSBC",
            "buy": "25.5488",
            "sell": "27.1979",
            "difference": "1.6491"
        }
    ]
}