{
    "timestamp": "2023-12-18 14:44:45",
    "data": [
        {
            "bank": "Kapalicarsi",
            "buy": "29.0550",
            "sell": "29.0650",
            "difference": "0.0100"
        },
        {
            "bank": "Altinkaynak",
            "buy": "28.9520",
            "sell": "29.1020",
            "difference": "0.1500"
        },
        {
            "bank": "Harem",
            "buy": "29.0420",
            "sell": "29.0720",
            "difference": "0.0300"
        },
        {
            "bank": "Odaci",
            "buy": "29.0250",
            "sell": "29.1150",
            "difference": "0.0900"
        },
        {
            "bank": "Venus",
            "buy": "29.0410",
            "sell": "29.0720",
            "difference": "0.0310"
        },
        {
            "bank": "Akbank",
            "buy": "28.5160",
            "sell": "29.7160",
            "difference": "1.2000"
        },
        {
            "bank": "Albaraka Türk",
            "buy": "28.8000",
            "sell": "29.3100",
            "difference": "0.5100"
        },
        {
            "bank": "Alternatif Bank",
            "buy": "27.8990",
            "sell": "31.3010",
            "difference": "3.4020"
        },
        {
            "bank": "Anadolubank",
            "buy": "28.6223",
            "sell": "29.5191",
            "difference": "0.8968"
        },
        {
            "bank": "CEPTETEB",
            "buy": "28.8820",
            "sell": "29.4990",
            "difference": "0.6170"
        },
        {
            "bank": "Denizbank",
            "buy": "28.7450",
            "sell": "29.5951",
            "difference": "0.8501"
        },
        {
            "bank": "Enpara",
            "buy": "28.8350",
            "sell": "29.3100",
            "difference": "0.4750"
        },
        {
            "bank": "Garanti BBVA",
            "buy": "28.6270",
            "sell": "29.6270",
            "difference": "1.0000"
        },
        {
            "bank": "Halkbank",
            "buy": "28.3553",
            "sell": "30.0553",
            "difference": "1.7000"
        },
        {
            "bank": "HSBC",
            "buy": "28.9174",
            "sell": "29.3065",
            "difference": "0.3891"
        },
        {
            "bank": "ING Bank",
            "buy": "28.4210",
            "sell": "29.6336",
            "difference": "1.2126"
        },
        {
            "bank": "İş Bankası",
            "buy": "28.5752",
            "sell": "29.4573",
            "difference": "0.8821"
        },
        {
            "bank": "Kuveyt Turk",
            "buy": "28.4350",
            "sell": "29.3655",
            "difference": "0.9305"
        },
        {
            "bank": "Merkez Bankasi",
            "buy": "29.0053",
            "sell": "29.0576",
            "difference": "0.0523"
        },
        {
            "bank": "QNB Finansbank",
            "buy": "28.8000",
            "sell": "29.3600",
            "difference": "0.5600"
        },
        {
            "bank": "Sekerbank",
            "buy": "28.5834",
            "sell": "29.6326",
            "difference": "1.0492"
        },
        {
            "bank": "Turkiye Finans",
            "buy": "28.8445",
            "sell": "29.3939",
            "difference": "0.5494"
        },
        {
            "bank": "Vakifbank",
            "buy": "28.6730",
            "sell": "29.5790",
            "difference": "0.9060"
        },
        {
            "bank": "Vakif Katilim",
            "buy": "28.8238",
            "sell": "29.2858",
            "difference": "0.4620"
        },
        {
            "bank": "Yapikredi",
            "buy": "28.7855",
            "sell": "29.4583",
            "difference": "0.6728"
        },
        {
            "bank": "Ziraat Bankasi",
            "buy": "28.6326",
            "sell": "29.5356",
            "difference": "0.9030"
        },
        {
            "bank": "Ziraat Katilim",
            "buy": "28.6160",
            "sell": "29.6338",
            "difference": "1.0178"
        }
    ]
}