{
    "timestamp": "2023-11-01 09:24:34",
    "data": [
        {
            "bank": "Kapalicarsi",
            "buy": "28.3300",
            "sell": "28.3400",
            "difference": "0.0100"
        },
        {
            "bank": "Altinkaynak",
            "buy": "28.2590",
            "sell": "28.4100",
            "difference": "0.1510"
        },
        {
            "bank": "Harem",
            "buy": "28.3150",
            "sell": "28.3440",
            "difference": "0.0290"
        },
        {
            "bank": "Odaci",
            "buy": "28.2800",
            "sell": "28.3600",
            "difference": "0.0800"
        },
        {
            "bank": "Venus",
            "buy": "28.3250",
            "sell": "28.3430",
            "difference": "0.0180"
        },
        {
            "bank": "Akbank",
            "buy": "27.8510",
            "sell": "29.0510",
            "difference": "1.2000"
        },
        {
            "bank": "Albaraka Türk",
            "buy": "28.0760",
            "sell": "28.7280",
            "difference": "0.6520"
        },
        {
            "bank": "Alternatif Bank",
            "buy": "28.2540",
            "sell": "28.4570",
            "difference": "0.2030"
        },
        {
            "bank": "CEPTETEB",
            "buy": "28.1570",
            "sell": "28.7490",
            "difference": "0.5920"
        },
        {
            "bank": "Denizbank",
            "buy": "28.0167",
            "sell": "28.8668",
            "difference": "0.8501"
        },
        {
            "bank": "Enpara",
            "buy": "28.3030",
            "sell": "28.7780",
            "difference": "0.4750"
        },
        {
            "bank": "Garanti BBVA",
            "buy": "27.9040",
            "sell": "28.9040",
            "difference": "1.0000"
        },
        {
            "bank": "Halkbank",
            "buy": "28.0160",
            "sell": "28.9160",
            "difference": "0.9000"
        },
        {
            "bank": "HSBC",
            "buy": "28.2035",
            "sell": "28.5881",
            "difference": "0.3846"
        },
        {
            "bank": "ING Bank",
            "buy": "27.7040",
            "sell": "28.9136",
            "difference": "1.2096"
        },
        {
            "bank": "İş Bankası",
            "buy": "28.0731",
            "sell": "28.9915",
            "difference": "0.9184"
        },
        {
            "bank": "Kuveyt Turk",
            "buy": "28.0513",
            "sell": "28.5291",
            "difference": "0.4778"
        },
        {
            "bank": "Merkez Bankasi",
            "buy": "28.2366",
            "sell": "28.2874",
            "difference": "0.0508"
        },
        {
            "bank": "QNB Finansbank",
            "buy": "28.2660",
            "sell": "28.8260",
            "difference": "0.5600"
        },
        {
            "bank": "Sekerbank",
            "buy": "27.8460",
            "sell": "28.9320",
            "difference": "1.0860"
        },
        {
            "bank": "Turkiye Finans",
            "buy": "28.1256",
            "sell": "28.6749",
            "difference": "0.5493"
        },
        {
            "bank": "Vakifbank",
            "buy": "27.9365",
            "sell": "28.8425",
            "difference": "0.9060"
        },
        {
            "bank": "Vakif Katilim",
            "buy": "28.1017",
            "sell": "28.5550",
            "difference": "0.4533"
        },
        {
            "bank": "Yapikredi",
            "buy": "27.9456",
            "sell": "28.8980",
            "difference": "0.9524"
        },
        {
            "bank": "Ziraat Bankasi",
            "buy": "27.9176",
            "sell": "28.8830",
            "difference": "0.9654"
        },
        {
            "bank": "Ziraat Katilim",
            "buy": "27.9006",
            "sell": "28.8899",
            "difference": "0.9893"
        }
    ]
}