{
    "timestamp": "2023-05-19 06:27:26",
    "data": [
        {
            "bank": "Kapalicarsi",
            "buy": "20.4300",
            "sell": "20.4500",
            "difference": "0.0200"
        },
        {
            "bank": "Akbank",
            "buy": "19.5910",
            "sell": "21.7910",
            "difference": "2.2000"
        },
        {
            "bank": "Albaraka Türk",
            "buy": "19.5890",
            "sell": "21.7600",
            "difference": "2.1710"
        },
        {
            "bank": "Denizbank",
            "buy": "19.7740",
            "sell": "21.2441",
            "difference": "1.4701"
        },
        {
            "bank": "Enpara",
            "buy": "19.5250",
            "sell": "21.5100",
            "difference": "1.9850"
        },
        {
            "bank": "Garanti BBVA",
            "buy": "19.7770",
            "sell": "21.5770",
            "difference": "1.8000"
        },
        {
            "bank": "HSBC",
            "buy": "19.5774",
            "sell": "21.6949",
            "difference": "2.1175"
        },
        {
            "bank": "ING Bank",
            "buy": "19.7884",
            "sell": "21.5035",
            "difference": "1.7151"
        },
        {
            "bank": "İş Bankası",
            "buy": "19.5352",
            "sell": "21.6367",
            "difference": "2.1015"
        },
        {
            "bank": "Kuveyt Türk Senin Bankan",
            "buy": "19.8046",
            "sell": "21.7919",
            "difference": "1.9873"
        }
    ]
}