{
    "timestamp": "2023-10-23 07:06:24",
    "data": [
        {
            "bank": "Kapalicarsi",
            "buy": "28.1000",
            "sell": "28.1100",
            "difference": "0.0100"
        },
        {
            "bank": "Altinkaynak",
            "buy": "28.0270",
            "sell": "28.1900",
            "difference": "0.1630"
        },
        {
            "bank": "Harem",
            "buy": "28.0610",
            "sell": "28.1440",
            "difference": "0.0830"
        },
        {
            "bank": "Odaci",
            "buy": "28.0400",
            "sell": "28.1800",
            "difference": "0.1400"
        },
        {
            "bank": "Venus",
            "buy": "28.0680",
            "sell": "28.1210",
            "difference": "0.0530"
        },
        {
            "bank": "Akbank",
            "buy": "27.5950",
            "sell": "28.8950",
            "difference": "1.3000"
        },
        {
            "bank": "Albaraka Türk",
            "buy": "27.8000",
            "sell": "28.4510",
            "difference": "0.6510"
        },
        {
            "bank": "Alternatif Bank",
            "buy": "27.9780",
            "sell": "28.1810",
            "difference": "0.2030"
        },
        {
            "bank": "CEPTETEB",
            "buy": "27.8840",
            "sell": "28.4700",
            "difference": "0.5860"
        },
        {
            "bank": "Denizbank",
            "buy": "27.7403",
            "sell": "28.5904",
            "difference": "0.8501"
        },
        {
            "bank": "Enpara",
            "buy": "27.9255",
            "sell": "28.4505",
            "difference": "0.5250"
        },
        {
            "bank": "Garanti BBVA",
            "buy": "27.7310",
            "sell": "28.7310",
            "difference": "1.0000"
        },
        {
            "bank": "Halkbank",
            "buy": "27.7402",
            "sell": "28.6702",
            "difference": "0.9300"
        },
        {
            "bank": "HSBC",
            "buy": "27.9211",
            "sell": "28.3416",
            "difference": "0.4205"
        },
        {
            "bank": "ING Bank",
            "buy": "27.4269",
            "sell": "28.6371",
            "difference": "1.2102"
        },
        {
            "bank": "İş Bankası",
            "buy": "27.7955",
            "sell": "28.7118",
            "difference": "0.9163"
        },
        {
            "bank": "Kuveyt Turk",
            "buy": "27.8222",
            "sell": "28.2578",
            "difference": "0.4356"
        },
        {
            "bank": "Merkez Bankasi",
            "buy": "27.9714",
            "sell": "28.0218",
            "difference": "0.0504"
        },
        {
            "bank": "QNB Finansbank",
            "buy": "27.8905",
            "sell": "28.5005",
            "difference": "0.6100"
        },
        {
            "bank": "Sekerbank",
            "buy": "27.7564",
            "sell": "28.7390",
            "difference": "0.9826"
        },
        {
            "bank": "Turkiye Finans",
            "buy": "27.8459",
            "sell": "28.3955",
            "difference": "0.5496"
        },
        {
            "bank": "Vakifbank",
            "buy": "27.8875",
            "sell": "28.3875",
            "difference": "0.5000"
        },
        {
            "bank": "Vakif Katilim",
            "buy": "27.8262",
            "sell": "28.2750",
            "difference": "0.4488"
        },
        {
            "bank": "Yapikredi",
            "buy": "27.7496",
            "sell": "28.7336",
            "difference": "0.9840"
        },
        {
            "bank": "Ziraat Bankasi",
            "buy": "27.6412",
            "sell": "28.5970",
            "difference": "0.9558"
        },
        {
            "bank": "Ziraat Katilim",
            "buy": "27.6278",
            "sell": "28.6080",
            "difference": "0.9802"
        }
    ]
}