{
    "timestamp": "2023-11-15 10:06:51",
    "data": [
        {
            "bank": "Kapalicarsi",
            "buy": "28.6895",
            "sell": "28.6995",
            "difference": "0.0100"
        },
        {
            "bank": "Altinkaynak",
            "buy": "28.6000",
            "sell": "28.7520",
            "difference": "0.1520"
        },
        {
            "bank": "Harem",
            "buy": "28.6870",
            "sell": "28.7120",
            "difference": "0.0250"
        },
        {
            "bank": "Odaci",
            "buy": "28.6750",
            "sell": "28.7550",
            "difference": "0.0800"
        },
        {
            "bank": "Venus",
            "buy": "28.6940",
            "sell": "28.7120",
            "difference": "0.0180"
        },
        {
            "bank": "Akbank",
            "buy": "28.1320",
            "sell": "29.3320",
            "difference": "1.2000"
        },
        {
            "bank": "Albaraka Türk",
            "buy": "28.4220",
            "sell": "28.9730",
            "difference": "0.5510"
        },
        {
            "bank": "Alternatif Bank",
            "buy": "28.5890",
            "sell": "28.7850",
            "difference": "0.1960"
        },
        {
            "bank": "CEPTETEB",
            "buy": "28.5040",
            "sell": "29.1030",
            "difference": "0.5990"
        },
        {
            "bank": "Denizbank",
            "buy": "28.3607",
            "sell": "29.1608",
            "difference": "0.8001"
        },
        {
            "bank": "Enpara",
            "buy": "28.5470",
            "sell": "28.9220",
            "difference": "0.3750"
        },
        {
            "bank": "Garanti BBVA",
            "buy": "28.2490",
            "sell": "29.2490",
            "difference": "1.0000"
        },
        {
            "bank": "Halkbank",
            "buy": "28.2922",
            "sell": "29.2222",
            "difference": "0.9300"
        },
        {
            "bank": "HSBC",
            "buy": "28.5448",
            "sell": "28.9253",
            "difference": "0.3805"
        },
        {
            "bank": "ING Bank",
            "buy": "28.0501",
            "sell": "29.2585",
            "difference": "1.2084"
        },
        {
            "bank": "İş Bankası",
            "buy": "28.2315",
            "sell": "29.2873",
            "difference": "1.0558"
        },
        {
            "bank": "Kuveyt Turk",
            "buy": "28.4377",
            "sell": "28.7830",
            "difference": "0.3453"
        },
        {
            "bank": "Merkez Bankasi",
            "buy": "28.5826",
            "sell": "28.6341",
            "difference": "0.0515"
        },
        {
            "bank": "QNB Finansbank",
            "buy": "28.5120",
            "sell": "28.9720",
            "difference": "0.4600"
        },
        {
            "bank": "Sekerbank",
            "buy": "28.2136",
            "sell": "29.2059",
            "difference": "0.9923"
        },
        {
            "bank": "Turkiye Finans",
            "buy": "28.4640",
            "sell": "29.0137",
            "difference": "0.5497"
        },
        {
            "bank": "Vakifbank",
            "buy": "28.3030",
            "sell": "29.2090",
            "difference": "0.9060"
        },
        {
            "bank": "Vakif Katilim",
            "buy": "28.4718",
            "sell": "28.8732",
            "difference": "0.4014"
        },
        {
            "bank": "Yapikredi",
            "buy": "28.3665",
            "sell": "29.0395",
            "difference": "0.6730"
        },
        {
            "bank": "Ziraat Bankasi",
            "buy": "28.2544",
            "sell": "29.2314",
            "difference": "0.9770"
        },
        {
            "bank": "Ziraat Katilim",
            "buy": "28.2410",
            "sell": "29.2421",
            "difference": "1.0011"
        }
    ]
}