{
    "timestamp": "2023-12-11 03:44:28",
    "data": [
        {
            "bank": "Kapalicarsi",
            "buy": "29.0200",
            "sell": "29.0300",
            "difference": "0.0100"
        },
        {
            "bank": "Altinkaynak",
            "buy": "28.9300",
            "sell": "29.0600",
            "difference": "0.1300"
        },
        {
            "bank": "Harem",
            "buy": "28.9150",
            "sell": "29.0730",
            "difference": "0.1580"
        },
        {
            "bank": "Odaci",
            "buy": "29.0350",
            "sell": "29.0650",
            "difference": "0.0300"
        },
        {
            "bank": "Venus",
            "buy": "28.9410",
            "sell": "29.0270",
            "difference": "0.0860"
        },
        {
            "bank": "Akbank",
            "buy": "28.4290",
            "sell": "30.2290",
            "difference": "1.8000"
        },
        {
            "bank": "Albaraka Türk",
            "buy": "28.1200",
            "sell": "29.8410",
            "difference": "1.7210"
        },
        {
            "bank": "Alternatif Bank",
            "buy": "27.3990",
            "sell": "30.8010",
            "difference": "3.4020"
        },
        {
            "bank": "Anadolubank",
            "buy": "28.1912",
            "sell": "30.1305",
            "difference": "1.9393"
        },
        {
            "bank": "CEPTETEB",
            "buy": "28.3480",
            "sell": "29.8050",
            "difference": "1.4570"
        },
        {
            "bank": "Denizbank",
            "buy": "28.5505",
            "sell": "29.6506",
            "difference": "1.1001"
        },
        {
            "bank": "Enpara",
            "buy": "28.6625",
            "sell": "29.5400",
            "difference": "0.8775"
        },
        {
            "bank": "Garanti BBVA",
            "buy": "28.3960",
            "sell": "30.1960",
            "difference": "1.8000"
        },
        {
            "bank": "Halkbank",
            "buy": "28.2750",
            "sell": "29.9750",
            "difference": "1.7000"
        },
        {
            "bank": "HSBC",
            "buy": "28.6670",
            "sell": "29.7576",
            "difference": "1.0906"
        },
        {
            "bank": "ING Bank",
            "buy": "27.9890",
            "sell": "29.8047",
            "difference": "1.8157"
        },
        {
            "bank": "İş Bankası",
            "buy": "28.2384",
            "sell": "30.1973",
            "difference": "1.9589"
        },
        {
            "bank": "Kuveyt Turk",
            "buy": "27.9286",
            "sell": "29.4419",
            "difference": "1.5133"
        },
        {
            "bank": "Merkez Bankasi",
            "buy": "28.8974",
            "sell": "28.9495",
            "difference": "0.0521"
        },
        {
            "bank": "QNB Finansbank",
            "buy": "28.6275",
            "sell": "29.5900",
            "difference": "0.9625"
        },
        {
            "bank": "Sekerbank",
            "buy": "27.8820",
            "sell": "29.9180",
            "difference": "2.0360"
        },
        {
            "bank": "Turkiye Finans",
            "buy": "28.7602",
            "sell": "29.3296",
            "difference": "0.5694"
        },
        {
            "bank": "Vakifbank",
            "buy": "28.2755",
            "sell": "29.9755",
            "difference": "1.7000"
        },
        {
            "bank": "Vakif Katilim",
            "buy": "28.1978",
            "sell": "29.3280",
            "difference": "1.1302"
        },
        {
            "bank": "Yapikredi",
            "buy": "28.6871",
            "sell": "29.5732",
            "difference": "0.8861"
        },
        {
            "bank": "Ziraat Bankasi",
            "buy": "28.2641",
            "sell": "29.9758",
            "difference": "1.7117"
        },
        {
            "bank": "Ziraat Katilim",
            "buy": "26.5413",
            "sell": "31.6221",
            "difference": "5.0808"
        }
    ]
}